wca_allauth/__init__.py
wca_allauth/apps.py
wca_allauth/provider.py
wca_allauth/urls.py
wca_allauth/views.py
wca_django_allauth-1.0.1.dist-info/LICENSE
wca_django_allauth-1.0.1.dist-info/METADATA
wca_django_allauth-1.0.1.dist-info/WHEEL
wca_django_allauth-1.0.1.dist-info/top_level.txt
wca_django_allauth-1.0.1.dist-info/RECORD
